gist_magic/__init__.py
gist_magic/extensions/__init__.py
gist_magic/extensions/gist.py
gist_magic/extensions/pretty.py
gist_magic-0.2.1.dist-info/DESCRIPTION.rst
gist_magic-0.2.1.dist-info/METADATA
gist_magic-0.2.1.dist-info/RECORD
gist_magic-0.2.1.dist-info/WHEEL
gist_magic-0.2.1.dist-info/metadata.json
gist_magic-0.2.1.dist-info/top_level.txt
