Metadata-Version: 2.0
Name: gist-magic
Version: 0.2.1
Summary: IPython magics to work with gists
Home-page: https://github.com/pramukta/gist-magic
Author: Pramukta Kumar
Author-email: pramukta.kumar@timbr.io
License: MIT
Platform: UNKNOWN
Requires-Dist: ipython
Requires-Dist: markdown
Requires-Dist: py-gfm
Requires-Dist: pygithub3
